{
  "dependencies": [
    "blooms"
  ],
  "tasks": {
    "andesite_alloy": {
      "type": "heracles:item",
      "item": "create:andesite_alloy",
      "amount": 2,
      "collection": "AUTOMATIC"
    }
  },
  "rewards": {},
  "display": {
    "subtitle": {
      "text": ""
    },
    "description": [
      ""
    ],
    "groups": {
      "Introduction": {
        "position": [
          6,
          191
        ]
      }
    },
    "icon": {
      "item": {
        "id": "create:andesite_alloy",
        "count": 1
      },
      "type": "heracles:item"
    },
    "icon_background": "heracles:textures/gui/quest_backgrounds/default.png",
    "title": {
      "translate": "Andesite Alloy"
    }
  },
  "settings": {
    "unlockNotification": false,
    "showDependencyArrow": true,
    "repeatable": false,
    "individual_progress": false,
    "hidden": "LOCKED"
  }
}