{
  "dependencies": [
    "bronze_brick_casing"
  ],
  "tasks": {
    "0BA366648050021A": {
      "type": "heracles:item",
      "item": "gtceu:lp_steam_forge_hammer",
      "nbt": {},
      "amount": 1,
      "collection": "AUTOMATIC"
    }
  },
  "rewards": {
    "lootbag": {
      "item": {
        "id": "lootbags:loot_bag",
        "count": 1,
        "nbt": {
          "Type": "COMMON",
          "Color": 13882323,
          "Loot": "lootbags:kjs/3ui6gksr7gxl82e5t9pkch2ls",
          "Name": "Lootbag (ULV Age)"
        }
      },
      "type": "heracles:item"
    }
  },
  "display": {
    "subtitle": {
      "text": ""
    },
    "description": [
      "You'll appreciate this machine alot. It can make plates much cheaper than hammers."
    ],
    "groups": {
      "ULV/ULS - Humble Beginnings": {
        "position": [
          -192,
          -144
        ]
      }
    },
    "icon": {
      "item": {
        "id": "gtceu:lp_steam_forge_hammer",
        "count": 1
      },
      "type": "heracles:item"
    },
    "icon_background": "heracles:textures/gui/quest_backgrounds/default.png",
    "title": {
      "translate": "Steam Forge Hammer"
    }
  },
  "settings": {
    "unlockNotification": false,
    "showDependencyArrow": true,
    "repeatable": false,
    "individual_progress": false,
    "hidden": "LOCKED"
  }
}