{
  "dependencies": [
    "steam_boilers"
  ],
  "tasks": {
    "35995E201BBE557D": {
      "type": "heracles:item",
      "item": "#gbth:steam_extractors",
      "nbt": {
        "items": [
          {
            "Count": 1,
            "id": "gtceu:lp_steam_extractor"
          },
          {
            "Count": 1,
            "id": "gtceu:hp_steam_extractor"
          }
        ]
      },
      "amount": 1,
      "collection": "AUTOMATIC",
      "title": "",
      "icon": {
        "item": {
          "id": "minecraft:air",
          "count": 0
        },
        "type": "heracles:item"
      }
    }
  },
  "rewards": {},
  "display": {
    "subtitle": {
      "text": ""
    },
    "description": [
      "<task task=\"35995E201BBE557D\" quest=\"70BDF42738F465DC\"/>",
      "<hr/>",
      "Turns stuff to liquid or extracts substances."
    ],
    "groups": {
      "ULV/ULS - Humble Beginnings..": {
        "position": [
          -48,
          -48
        ]
      }
    },
    "icon": {
      "item": {
        "id": "gtceu:lp_steam_extractor",
        "count": 1
      },
      "type": "heracles:item"
    },
    "icon_background": "heracles:textures/gui/quest_backgrounds/default.png",
    "title": {
      "translate": "Steam Extractor"
    }
  },
  "settings": {
    "unlockNotification": false,
    "showDependencyArrow": true,
    "repeatable": false,
    "individual_progress": false,
    "hidden": "LOCKED"
  }
}